consolepi/__about__.py
consolepi/__init__.py
consolepi/config.py
consolepi/consolepi.py
consolepi/exec.py
consolepi/gdrive.py
consolepi/local.py
consolepi/menu.py
consolepi/models.py
consolepi/remotes.py
consolepi/udevrename.py
consolepi/utils.py
consolepi/power/__init__.py
consolepi/power/dlirest.py
consolepi/power/outlets.py
consolepi-0.0.11.dist-info/METADATA
consolepi-0.0.11.dist-info/WHEEL
consolepi-0.0.11.dist-info/licenses/LICENSE
consolepi-0.0.11.dist-info/RECORD
