Metadata-Version: 2.4
Name: consolepi
Version: 0.0.11
Summary: Acts as a serial Console Server, allowing you to remotely connect to ConsolePi via Telnet/SSH/bluetooth to gain Console Access to devices connected to local or remote ConsolePis via USB to serial adapters (i.e. Switches, Routers, Access Points... anything with a serial port).
Project-URL: Documentation, https://consolepi.readthedocs.io
Project-URL: Issues, https://github.com/Pack3tL0ss/consolepi/issues
Project-URL: Source, https://github.com/Pack3tL0ss/consolepi
Author-email: Pack3tL0ss <wade99@gmail.com>
License-Expression: MIT
License-File: LICENSE
Classifier: Development Status :: 4 - Beta
Classifier: Programming Language :: Python
Classifier: Programming Language :: Python :: 3.8
Classifier: Programming Language :: Python :: 3.9
Classifier: Programming Language :: Python :: 3.10
Classifier: Programming Language :: Python :: 3.11
Classifier: Programming Language :: Python :: 3.12
Classifier: Programming Language :: Python :: Implementation :: CPython
Classifier: Programming Language :: Python :: Implementation :: PyPy
Requires-Python: >=3.8
Requires-Dist: aiohttp>=3.10.11
Requires-Dist: dlipower>=1.0.176
Requires-Dist: fastapi>=0.103.2
Requires-Dist: google-api-python-client>=2.103.0
Requires-Dist: google-auth-oauthlib>=1.1.0
Requires-Dist: halo>=0.0.31
Requires-Dist: in-place>=0.5.0
Requires-Dist: jinja2>=3.1.2
Requires-Dist: log-symbols>=0.0.14
Requires-Dist: netifaces>=0.11.0
Requires-Dist: paramiko>=3.3.1
Requires-Dist: psutil>=5.9.5
Requires-Dist: pydantic>=2.4.2
Requires-Dist: pyudev>=0.24.1
Requires-Dist: pyyaml>=6.0.1
Requires-Dist: requests>=2.31.0
Requires-Dist: rich>=13.6.0
Requires-Dist: setproctitle>=1.3.3
Requires-Dist: starlette>=0.27.0
Requires-Dist: uvicorn>=0.23.2
Requires-Dist: zeroconf>=0.115.2
